micropython_stts22h/__init__.py
micropython_stts22h/i2c_helpers.py
micropython_stts22h/stts22h.py
micropython_stts22h-0.1.2.dist-info/LICENSE
micropython_stts22h-0.1.2.dist-info/METADATA
micropython_stts22h-0.1.2.dist-info/WHEEL
micropython_stts22h-0.1.2.dist-info/top_level.txt
micropython_stts22h-0.1.2.dist-info/RECORD
