Metadata-Version: 2.1
Name: micropython-stts22h
Version: 0.1.2
Summary: MicroPython Driver for the STTS22H Temperature Sensor
Author-email: JDM <xxyx@mailmeto.mozmail.com>
License: MIT
Project-URL: Homepage, https://github.com/jposada202020/MicroPython_STTS22H
Keywords: sensor,stts22h,temperature,sensor,st,micropython,celsius
Classifier: Intended Audience :: Developers
Classifier: Topic :: Software Development :: Libraries
Classifier: Topic :: Software Development :: Embedded Systems
Classifier: Topic :: System :: Hardware
Classifier: License :: OSI Approved :: MIT License
Classifier: Programming Language :: Python :: Implementation :: MicroPython
License-File: LICENSE
